arbmark/__init__.py
arbmark/__main__.py
arbmark/functions/__init__.py
arbmark/functions/aggregation.py
arbmark/functions/categorize_ranges.py
arbmark/functions/files.py
arbmark/functions/interval.py
arbmark/functions/merge.py
arbmark/functions/quarter.py
arbmark/functions/reference.py
arbmark/functions/statbank_formats.py
arbmark/functions/workdays.py
arbmark/groups/__init__.py
arbmark/groups/age.py
arbmark/groups/company_size.py
arbmark/groups/country_origin.py
arbmark/groups/nace.py
arbmark/groups/occupation.py
arbmark/groups/region.py
arbmark/groups/sector.py
arbmark/groups/shift_work.py
arbmark/py.typed
ssb_arbmark_fagfunksjoner-0.0.28.dist-info/LICENSE
ssb_arbmark_fagfunksjoner-0.0.28.dist-info/METADATA
ssb_arbmark_fagfunksjoner-0.0.28.dist-info/WHEEL
ssb_arbmark_fagfunksjoner-0.0.28.dist-info/entry_points.txt
ssb_arbmark_fagfunksjoner-0.0.28.dist-info/RECORD
