Metadata-Version: 2.1
Name: ssb-arbmark-fagfunksjoner
Version: 0.0.28
Summary: SSB Arbeidsmarked og lønn Fag-fellesfunksjoner
Home-page: https://github.com/statisticsnorway/ssb-arbmark-fagfunksjoner
License: MIT
Author: Jan Sebastian Rothe
Author-email: jsr@ssb.no
Requires-Python: >=3.10,<4
Classifier: Development Status :: 4 - Beta
Classifier: License :: OSI Approved :: MIT License
Classifier: Programming Language :: Python :: 3
Classifier: Programming Language :: Python :: 3.10
Classifier: Programming Language :: Python :: 3.11
Classifier: Programming Language :: Python :: 3.12
Classifier: Programming Language :: Python :: 3.13
Requires-Dist: click (>=8.0.1)
Requires-Dist: dapla-toolbelt (>=3.2.0)
Requires-Dist: holidays (<1.0)
Requires-Dist: numpy (>=2.0.0)
Requires-Dist: pandas (>=1.5.3)
Requires-Dist: pandas-stubs (>=2.1.1.230928)
Requires-Dist: ssb-klass-python (>=0.0.9)
Project-URL: Changelog, https://github.com/statisticsnorway/ssb-arbmark-fagfunksjoner/releases
Project-URL: Documentation, https://statisticsnorway.github.io/ssb-arbmark-fagfunksjoner
Project-URL: Repository, https://github.com/statisticsnorway/ssb-arbmark-fagfunksjoner
